cupper.py
cupper-0.0.4.dist-info/METADATA
cupper-0.0.4.dist-info/RECORD
cupper-0.0.4.dist-info/WHEEL
cupper-0.0.4.dist-info/entry_points.txt
cupper-0.0.4.dist-info/top_level.txt
