Metadata-Version: 2.1
Name: cupper
Version: 0.0.4
Summary: Cookie-cutter updater
Home-page: http://github.com/senseyeio/cupper
Author: Mike Jewell
Author-email: mike.jewell@senseye.io
License: MIT
Platform: UNKNOWN
Requires-Dist: cookiecutter
Requires-Dist: subprocess32
